syncmaster/__init__.py
syncmaster/_modidx.py
syncmaster/analysis.py
syncmaster/device.py
syncmaster-1.0.6.dist-info/LICENSE
syncmaster-1.0.6.dist-info/METADATA
syncmaster-1.0.6.dist-info/WHEEL
syncmaster-1.0.6.dist-info/entry_points.txt
syncmaster-1.0.6.dist-info/top_level.txt
syncmaster-1.0.6.dist-info/RECORD
