Metadata-Version: 2.1
Name: syncmaster
Version: 1.0.6
Summary: Device and drivers for generating trigger signals to synchronise recorded signals with behavioural data
Home-page: https://github.com/conorkeogh/syncmaster
Author: Conor Keogh
Author-email: conor.keogh@nds.ox.ac.uk
License: Apache Software License 2.0
Keywords: nbdev jupyter notebook python
Classifier: Development Status :: 4 - Beta
Classifier: Intended Audience :: Developers
Classifier: Natural Language :: English
Classifier: Programming Language :: Python :: 3.7
Classifier: Programming Language :: Python :: 3.8
Classifier: Programming Language :: Python :: 3.9
Classifier: Programming Language :: Python :: 3.10
Classifier: License :: OSI Approved :: Apache Software License
Requires-Python: >=3.7
License-File: LICENSE
Requires-Dist: numpy
Requires-Dist: pyserial
Requires-Dist: matplotlib
Requires-Dist: seaborn
Provides-Extra: dev
